tuya_connector/__init__.py
tuya_connector/openapi.py
tuya_connector/openlogging.py
tuya_connector/openpulsar.py
tuya_connector/tuya_enums.py
tuya_connector/version.py
tuya_connector_python-0.1.2.dist-info/LICENSE
tuya_connector_python-0.1.2.dist-info/METADATA
tuya_connector_python-0.1.2.dist-info/WHEEL
tuya_connector_python-0.1.2.dist-info/entry_points.txt
tuya_connector_python-0.1.2.dist-info/top_level.txt
tuya_connector_python-0.1.2.dist-info/RECORD
