Metadata-Version: 2.1
Name: tuya-connector-python
Version: 0.1.2
Summary: The `tuya-connector-python` SDK is desinged to support open APIs and Pulsar Messages provided by Tuya.
Home-page: https://github.com/tuya/tuya-connector-python
Author: Tuya Inc.
Author-email: developer@tuya.com
License: MIT
Project-URL: Bug Tracker, https://github.com/tuya/tuya-connector-python/issues
Project-URL: Changes, https://github.com/tuya/tuya-connector-python/wiki/Tuya-Connector-Python-Release-Notes
Keywords: tuya iot cloud sdk python
Platform: UNKNOWN
Classifier: Development Status :: 4 - Beta
Classifier: License :: OSI Approved :: MIT License
Classifier: Operating System :: OS Independent
Classifier: Topic :: Software Development
Classifier: Programming Language :: Python :: 3
Classifier: Programming Language :: Python :: 3.6
Classifier: Programming Language :: Python :: 3.7
Classifier: Programming Language :: Python :: 3.8
Classifier: Programming Language :: Python :: 3.9
Classifier: Programming Language :: Python :: Implementation :: PyPy
Requires-Python: >=3.0
Provides-Extra: test
